{
  "element_kind": "activation_role",
  "element_key": "design_sun",
  "element_label": "Автоматическое ядро поведения",
  "language": "ru",
  "version": "v1",
  "source_quality": "expert_draft",
  "classic_markdown": "activation_role/design_sun · Автоматическое ядро поведения\n\nDesign Sun activation position — automatic central behavioral theme in activation composition.\n\n`design_sun` — это activation_position, где планетарная функция Sun соединяется со стороной Design.\n\n```text\nactivation_position = planet + side\ndesign_sun = Sun + Design\n```\n\nЭта позиция показывает, как конкретная gate+line тема становится автоматическим центральным проявлением в карте.\n\nВ классической логике Human Design Sun относится к центральной теме жизненного проявления. В ScanTalent это переводится как центральная рабочая тема конкретной gate+line активации.\n\nSun показывает центральную тему проявления. В Design-стороне эта центральность чаще видна не через самоописание, а через поведение, телесную механику, реактивность, рабочий тон и то, как человек проявляется в среде.\n\nSun добавляет теме функцию ядра:\n\n```text\nцентральность;\nзаметность;\nстабильный поведенческий тон;\nестественное проявление;\nвлияние на то, как человека считывают;\nтему, которая может быть видна раньше, чем она объяснена словами.\n```\n\nВ HR-переводе Design Sun помогает понять, что стоит наблюдать в поведении человека, а не только спрашивать в интервью.",
  "hr_translation_markdown": "## Короткая суть\n\nЭта позиция показывает тему, которая может проявляться в поведении человека автоматически: в действиях, реакциях, рабочем тоне, повторяющихся привычках и том, как его видят со стороны.\n\nЭто не скрытая слабость и не диагноз. Это функция конкретной темы в общей рабочей механике человека.\n\n## В работе\n\nВ работе такая тема может проявляться не столько через слова о себе, сколько через устойчивый поведенческий рисунок.\n\nОна может показывать:\n\n```text\nчто другие регулярно замечают в человеке;\nкакая тема проявляется в действиях без долгого объяснения;\nкакой рабочий тон человек приносит в среду;\nчто становится заметно в реальных задачах;\nкакая тема может включаться быстрее, чем человек успевает её осознанно сформулировать.\n```\n\n## Здоровое проявление\n\nЧеловек естественно проявляет эту тему в поведении, не пытаясь постоянно её объяснять или доказывать.\n\nВ здоровом проявлении эта тема может стать устойчивым рабочим вкладом: человек просто действует определённым образом, а команда видит повторяемую ценность в его поведении, реакциях, присутствии или способе включаться.\n\n## Искажённое проявление\n\nИскажённое проявление возникает, когда автоматическую тему начинают требовать как полностью осознанную стратегию или жёстко навешивают на человека как ярлык.\n\nЭто может выглядеть как:\n\n```text\nчеловек не может объяснить то, что другие в нём видят;\nсреда давит: “будь таким всегда”;\nавтоматическая реакция проявляется слишком резко или не к месту;\nчеловек пытается контролировать поведение, которое лучше сначала наблюдать;\nкоманда воспринимает повторяющийся паттерн без учёта контекста.\n```\n\n## Как использовать руководителю\n\nРуководителю полезно наблюдать эту тему в реальных рабочих ситуациях, а не опираться только на то, как человек рассказывает о себе.\n\nПрактически:\n\n```text\nсмотреть на повторяющееся поведение в задачах;\nне требовать мгновенного объяснения автоматических реакций;\nдавать человеку подходящий контекст, где тема проявляется естественно;\nсверять наблюдения с фактами, а не с догадками;\nне превращать автоматический паттерн в жёсткий ярлык.\n```\n\n## Что проверить в реальности\n\nПроверить стоит:\n\n```text\nзамечают ли эту тему другие люди;\nповторяется ли она в разных рабочих ситуациях;\nкак она проявляется под нагрузкой;\nподдерживается ли она навыками и реальным результатом;\nне является ли наблюдение эффектом конкретной среды, роли или стресса.\n```\n\n## Важное ограничение\n\nЭто не ярлык человека и не готовый HR-вывод. Позиция только уточняет функцию темы; итоговый вывод зависит от всей карты и реального рабочего поведения.",
  "pro_markdown": "## Позиция активации · Солнце Дизайна\n\n## Технический смысл\n\n`design_sun` — это activation_position, где планетарная функция Sun соединяется со стороной Design.\n\n```text\nactivation_position = planet + side\ndesign_sun = Sun + Design\n```\n\nЭта позиция показывает, как конкретная gate+line тема становится автоматическим центральным проявлением в карте.\n\nВ классической логике Human Design Sun относится к центральной теме жизненного проявления. В ScanTalent это переводится как центральная рабочая тема конкретной gate+line активации.\n\n## Planet function\n\nSun показывает центральную тему проявления. В Design-стороне эта центральность чаще видна не через самоописание, а через поведение, телесную механику, реактивность, рабочий тон и то, как человек проявляется в среде.\n\nSun добавляет теме функцию ядра:\n\n```text\nцентральность;\nзаметность;\nстабильный поведенческий тон;\nестественное проявление;\nвлияние на то, как человека считывают;\nтему, которая может быть видна раньше, чем она объяснена словами.\n```\n\nВ HR-переводе Design Sun помогает понять, что стоит наблюдать в поведении человека, а не только спрашивать в интервью.\n\n## Side function\n\nDesign показывает более автоматическую, телесную и менее осознаваемую сторону проявления.\n\nВ этой позиции тема может быть:\n\n```text\nзаметна другим людям;\nвидна в действиях;\nвидна в ритме и реакциях;\nсложнее доступна через прямое самоописание;\nустойчивее проявлена в поведении, чем в словах;\nособенно заметна в реальных задачах и под нагрузкой.\n```\n\nDesign не означает слабость, проблему, тень или “плохую неосознанность”. Это автоматический слой механики, который нужно наблюдать аккуратно и читать только в контексте всей карты.\n\n## Function in activation composition\n\nЭта позиция уточняет функцию темы в activation composition:\n\n```text\ngate + line + planet + side + activation_position\n```\n\n`design_sun` добавляет к gate+line теме функцию автоматического центрального проявления.\n\nПример логики чтения:\n\n```text\ngate = какая тема проявляется\nline = каким стилем тема проявляется\nSun = тема становится центральной\nDesign = тема проявляется автоматичнее, телеснее, поведенчески\ndesign_sun = автоматическое центральное проявление этой gate+line темы\n```\n\n## Contextual reading\n\nПозицию нельзя читать отдельно. Она уточняет тему gate и стиль line, но итоговое значение зависит от:\n\n```text\ntype\nstrategy\nauthority\nprofile\ndefined / open centers\nfull channel или hanging gate\nреального поведения\nнаблюдения команды\nусловий нагрузки\nрабочей среды\nсвязи с Earth axis\n```\n\nЕсли gate входит в полный канал, тема может проявляться как более устойчивый рабочий механизм. Если gate висит отдельно, её проявление может сильнее зависеть от внешнего контекста, партнёрских связок и условий среды.\n\nКогда будут готовы Earth activation_position cards, Design Sun желательно читать вместе с Earth, чтобы видеть не только автоматическое центральное проявление, но и то, через что оно стабилизируется.\n\n## Correct expression\n\nКорректное проявление возникает, когда автоматическая центральная тема получает подходящий контекст и не требует постоянного ментального контроля.\n\nВ корректном проявлении человек:\n\n```text\nестественно проявляет тему через поведение;\nне обязан сразу всё объяснять словами;\nпоказывает повторяемый рабочий паттерн;\nраскрывает тему в подходящей роли и среде;\nдействует в согласии с Type / Strategy / Authority;\nпозволяет теме подтверждаться через факты и наблюдения.\n```\n\n## Not-Self expression\n\nNot-Self проявление возникает, когда Design Sun читается изолированно или когда среда давит на автоматическую тему, превращая её в требование, ярлык или ожидание постоянного поведения.\n\nЭто может проявляться как:\n\n```text\nчеловека заставляют объяснять то, что лучше видно в поведении;\nавтоматическую реакцию принимают за весь характер;\nсреда требует “будь таким всегда”;\nчеловек пытается контролировать естественный паттерн через ум;\nпод нагрузкой центральная тема становится резкой, закрытой или защитной;\nAI делает вывод по наблюдаемому паттерну без gate, line и whole chart context.\n```\n\n## Interpretation limits\n\nЭта карточка описывает не самостоятельное значение Sun и не самостоятельное значение Design, а их совместную функцию внутри activation composition.\n\nНельзя делать вывод о человеке только по `design_sun`.\n\nНельзя трактовать Design как слабость, проблему, тень или отсутствие осознанности. Это автоматическая сторона проявления, которая может быть здоровой и ценной при корректном контексте.\n\nВ классической логике Human Design такая позиция читается только через gate, line и общую механику карты.",
  "talent_hints": [
    "помогает увидеть тему, которая естественно считывается в поведении человека",
    "показывает автоматический центральный паттерн, заметный в рабочих ситуациях",
    "помогает отличить наблюдаемое проявление от self-report",
    "может указывать на устойчивый рабочий тон или способ действия",
    "помогает AI учитывать, что не весь вклад человек сможет сразу объяснить словами"
  ],
  "risk_hints": [
    "риск навесить ярлык по наблюдаемому поведению",
    "риск требовать от человека полного объяснения автоматической темы",
    "риск принять реакцию под нагрузкой за постоянное качество",
    "риск недооценить тему, если человек не умеет о ней говорить",
    "риск считать Design проблемой или слабостью"
  ],
  "management_hints": [
    "наблюдать человека в реальных рабочих ситуациях",
    "использовать факты поведения, а не догадки",
    "не требовать мгновенного самоанализа по автоматической теме",
    "давать контекст, где тема может проявиться естественно",
    "обсуждать наблюдения мягко, через примеры и результат"
  ],
  "environment_hints": [
    "среда, где человека оценивают по реальному поведению и результату",
    "задачи, где тема может проявляться естественно",
    "достаточно времени для наблюдения повторяемого паттерна",
    "отсутствие давления “объясни себя прямо сейчас”",
    "команда, которая различает автоматическое проявление и жёсткий ярлык"
  ],
  "limitations": [
    "Не делать финальный вывод о человеке только по design_sun.",
    "Не использовать как профессию, должность или HR-роль.",
    "Не использовать для fit_score, role-fit, процентов соответствия или решения о найме.",
    "Не читать без gate и line.",
    "Не читать без контекста всей карты.",
    "Не считать Design проблемной или “неосознанной слабостью”.",
    "Не считать Sun всей картой или полной личностью человека.",
    "Не требовать, чтобы человек сразу объяснял Design-тему как осознанный мотив.",
    "Не принимать единичное наблюдение за устойчивый автоматический паттерн."
  ],
  "base_layers": {
    "title": "Автоматическое ядро поведения",
    "base_label": "Автоматическое ядро поведения",
    "plain_meaning": "Эта позиция показывает тему, которая может проявляться в поведении человека автоматически: в действиях, реакциях, рабочем тоне, повторяющихся привычках и том, как его видят со стороны.\n\nЭто не скрытая слабость и не диагноз. Это функция конкретной темы в общей рабочей механике человека.",
    "work_manifestation": "В работе такая тема может проявляться не столько через слова о себе, сколько через устойчивый поведенческий рисунок.\n\nОна может показывать:\n\n```text\nчто другие регулярно замечают в человеке;\nкакая тема проявляется в действиях без долгого объяснения;\nкакой рабочий тон человек приносит в среду;\nчто становится заметно в реальных задачах;\nкакая тема может включаться быстрее, чем человек успевает её осознанно сформулировать.\n```",
    "healthy_expression": "Человек естественно проявляет эту тему в поведении, не пытаясь постоянно её объяснять или доказывать.\n\nВ здоровом проявлении эта тема может стать устойчивым рабочим вкладом: человек просто действует определённым образом, а команда видит повторяемую ценность в его поведении, реакциях, присутствии или способе включаться.",
    "distorted_expression": "Искажённое проявление возникает, когда автоматическую тему начинают требовать как полностью осознанную стратегию или жёстко навешивают на человека как ярлык.\n\nЭто может выглядеть как:\n\n```text\nчеловек не может объяснить то, что другие в нём видят;\nсреда давит: “будь таким всегда”;\nавтоматическая реакция проявляется слишком резко или не к месту;\nчеловек пытается контролировать поведение, которое лучше сначала наблюдать;\nкоманда воспринимает повторяющийся паттерн без учёта контекста.\n```",
    "strengths": "помогает увидеть тему, которая естественно считывается в поведении человека; показывает автоматический центральный паттерн, заметный в рабочих ситуациях; помогает отличить наблюдаемое проявление от self-report; может указывать на устойчивый рабочий тон или способ действия; помогает AI учитывать, что не весь вклад человек сможет сразу объяснить словами",
    "risks": "риск навесить ярлык по наблюдаемому поведению; риск требовать от человека полного объяснения автоматической темы; риск принять реакцию под нагрузкой за постоянное качество; риск недооценить тему, если человек не умеет о ней говорить; риск считать Design проблемой или слабостью",
    "when_it_works_best": "Руководителю полезно наблюдать эту тему в реальных рабочих ситуациях, а не опираться только на то, как человек рассказывает о себе.\n\nПрактически:\n\n```text\nсмотреть на повторяющееся поведение в задачах;\nне требовать мгновенного объяснения автоматических реакций;\nдавать человеку подходящий контекст, где тема проявляется естественно;\nсверять наблюдения с фактами, а не с догадками;\nне превращать автоматический паттерн в жёсткий ярлык.\n```",
    "when_talent_is_not_revealed": "Искажённое проявление возникает, когда автоматическую тему начинают требовать как полностью осознанную стратегию или жёстко навешивают на человека как ярлык.\n\nЭто может выглядеть как:\n\n```text\nчеловек не может объяснить то, что другие в нём видят;\nсреда давит: “будь таким всегда”;\nавтоматическая реакция проявляется слишком резко или не к месту;\nчеловек пытается контролировать поведение, которое лучше сначала наблюдать;\nкоманда воспринимает повторяющийся паттерн без учёта контекста.\n```",
    "development_hints": [
      "учиться замечать, как тема проявляется в поведении",
      "собирать обратную связь от среды без самообвинения",
      "отличать естественный паттерн от реакции на стресс",
      "переводить наблюдаемое поведение в осознанные рабочие выводы",
      "не пытаться контролировать автоматическую тему только через ум"
    ],
    "communication_hints": [
      "человеку может быть проще показать тему действием, чем объяснить словами",
      "в интервью полезны вопросы о конкретных ситуациях и наблюдениях других людей",
      "обратная связь должна быть привязана к фактам поведения",
      "не стоит требовать мгновенного объяснения автоматической реакции",
      "полезно сверять self-report с наблюдаемым паттерном"
    ],
    "reality_check": "Проверить стоит:\n\n```text\nзамечают ли эту тему другие люди;\nповторяется ли она в разных рабочих ситуациях;\nкак она проявляется под нагрузкой;\nподдерживается ли она навыками и реальным результатом;\nне является ли наблюдение эффектом конкретной среды, роли или стресса.\n```",
    "important_note": "Это не ярлык человека и не готовый HR-вывод. Позиция только уточняет функцию темы; итоговый вывод зависит от всей карты и реального рабочего поведения."
  },
  "pro_layers": {
    "hd_meaning": "`design_sun` — это activation_position, где планетарная функция Sun соединяется со стороной Design.\n\n```text\nactivation_position = planet + side\ndesign_sun = Sun + Design\n```\n\nЭта позиция показывает, как конкретная gate+line тема становится автоматическим центральным проявлением в карте.\n\nВ классической логике Human Design Sun относится к центральной теме жизненного проявления. В ScanTalent это переводится как центральная рабочая тема конкретной gate+line активации.",
    "mechanics": "Эта позиция уточняет функцию темы в activation composition:\n\n```text\ngate + line + planet + side + activation_position\n```\n\n`design_sun` добавляет к gate+line теме функцию автоматического центрального проявления.\n\nПример логики чтения:\n\n```text\ngate = какая тема проявляется\nline = каким стилем тема проявляется\nSun = тема становится центральной\nDesign = тема проявляется автоматичнее, телеснее, поведенчески\ndesign_sun = автоматическое центральное проявление этой gate+line темы\n```",
    "planet_function": "Sun показывает центральную тему проявления. В Design-стороне эта центральность чаще видна не через самоописание, а через поведение, телесную механику, реактивность, рабочий тон и то, как человек проявляется в среде.\n\nSun добавляет теме функцию ядра:\n\n```text\nцентральность;\nзаметность;\nстабильный поведенческий тон;\nестественное проявление;\nвлияние на то, как человека считывают;\nтему, которая может быть видна раньше, чем она объяснена словами.\n```\n\nВ HR-переводе Design Sun помогает понять, что стоит наблюдать в поведении человека, а не только спрашивать в интервью.",
    "side_function": "Design показывает более автоматическую, телесную и менее осознаваемую сторону проявления.\n\nВ этой позиции тема может быть:\n\n```text\nзаметна другим людям;\nвидна в действиях;\nвидна в ритме и реакциях;\nсложнее доступна через прямое самоописание;\nустойчивее проявлена в поведении, чем в словах;\nособенно заметна в реальных задачах и под нагрузкой.\n```\n\nDesign не означает слабость, проблему, тень или “плохую неосознанность”. Это автоматический слой механики, который нужно наблюдать аккуратно и читать только в контексте всей карты.",
    "source_logic": "activation_role/design_sun describes activation_position function (planet + side) for gate+line themes. Final reading depends on gate, line, full activation key, profile, type, authority and whole chart context.",
    "contextual_reading": "Позицию нельзя читать отдельно. Она уточняет тему gate и стиль line, но итоговое значение зависит от:\n\n```text\ntype\nstrategy\nauthority\nprofile\ndefined / open centers\nfull channel или hanging gate\nреального поведения\nнаблюдения команды\nусловий нагрузки\nрабочей среды\nсвязи с Earth axis\n```\n\nЕсли gate входит в полный канал, тема может проявляться как более устойчивый рабочий механизм. Если gate висит отдельно, её проявление может сильнее зависеть от внешнего контекста, партнёрских связок и условий среды.\n\nКогда будут готовы Earth activation_position cards, Design Sun желательно читать вместе с Earth, чтобы видеть не только автоматическое центральное проявление, но и то, через что оно стабилизируется.",
    "correct_expression": "Корректное проявление возникает, когда автоматическая центральная тема получает подходящий контекст и не требует постоянного ментального контроля.\n\nВ корректном проявлении человек:\n\n```text\nестественно проявляет тему через поведение;\nне обязан сразу всё объяснять словами;\nпоказывает повторяемый рабочий паттерн;\nраскрывает тему в подходящей роли и среде;\nдействует в согласии с Type / Strategy / Authority;\nпозволяет теме подтверждаться через факты и наблюдения.\n```",
    "not_self_expression": "Not-Self проявление возникает, когда Design Sun читается изолированно или когда среда давит на автоматическую тему, превращая её в требование, ярлык или ожидание постоянного поведения.\n\nЭто может проявляться как:\n\n```text\nчеловека заставляют объяснять то, что лучше видно в поведении;\nавтоматическую реакцию принимают за весь характер;\nсреда требует “будь таким всегда”;\nчеловек пытается контролировать естественный паттерн через ум;\nпод нагрузкой центральная тема становится резкой, закрытой или защитной;\nAI делает вывод по наблюдаемому паттерну без gate, line и whole chart context.\n```",
    "pro_not_self": "Not-Self проявление возникает, когда Design Sun читается изолированно от gate, line, Strategy, Authority, channel context и whole chart context. Автоматическая тема может быть ошибочно принята за весь характер человека или за проблему, хотя она является частью механики проявления.",
    "interpretation_limitations": "Эта карточка описывает не самостоятельное значение Sun и не самостоятельное значение Design, а их совместную функцию внутри activation composition.\n\nНельзя делать вывод о человеке только по `design_sun`.\n\nНельзя трактовать Design как слабость, проблему, тень или отсутствие осознанности. Это автоматическая сторона проявления, которая может быть здоровой и ценной при корректном контексте.\n\nВ классической логике Human Design такая позиция читается только через gate, line и общую механику карты.",
    "card_metadata": {
      "methodological_name": "activation_position",
      "editorial_version": "v0.1.1",
      "status": "approved_after_editorial_review",
      "ui_base_label": "Автоматическое ядро поведения",
      "ui_pro_label": "Позиция активации · Солнце Дизайна",
      "primary_layer_key": "pro_foundation",
      "link_target": "element://activation_role/design_sun",
      "source_file": "supabase/reference/element_cards/source/activation_role_design_sun.md",
      "used_in_layers": [
        "pro_foundation",
        "main_talents",
        "work_style",
        "development_potential",
        "risks_and_distortions",
        "management_and_environment"
      ],
      "methodology_note": "activation_position card: describes planet+side function in activation composition, not a final person label. Read through gate, line, full activation and whole chart context."
    },
    "ai_source_rules": {
      "allowed_uses": [
        "использовать как компонент activation composition",
        "уточнять функцию gate+line темы как автоматического центрального проявления",
        "помогать AI ранжировать Sun activations в main_talents и pro_foundation",
        "использовать для различения self-report и наблюдаемого поведения",
        "использовать в Pro-основании",
        "использовать в AI Digest",
        "использовать для source chips"
      ],
      "forbidden_uses": [
        "не использовать как самостоятельный вывод о человеке",
        "не превращать в должность, профессию или HR-роль",
        "не использовать для hire/no-hire decision",
        "не использовать без gate, line и whole chart context",
        "не делать вывод “это вся личность человека”",
        "не считать Design слабостью, проблемой или тенью",
        "не требовать от Design-темы полного self-report",
        "не дублировать полные planet-card и side-card внутри позиции"
      ],
      "preferred_layers": [
        "main_talents",
        "work_style",
        "development_potential",
        "risks_and_distortions",
        "management_and_environment",
        "pro_foundation"
      ],
      "conditional_layers": [
        "communication_and_influence, если gate/channel связаны с выражением, голосом, объяснением или влиянием",
        "decision_and_stability, если gate/channel связаны с устойчивостью, давлением, страхом, инстинктом или принятием решений"
      ],
      "source_priority": "supporting",
      "source_priority_note": "Default = supporting, потому что activation_position сама по себе не является полным source item. Может стать primary внутри layer-specific source selection, если рассматривается full activation и gate+line тема Sun является центральной, повторяющейся или channel-backed.",
      "ai_must_check": [
        "gate",
        "line",
        "planet",
        "side",
        "full activation key",
        "full channel / hanging gate context",
        "type / strategy / authority",
        "profile",
        "observed behavior if available",
        "related Earth activation when available",
        "source_role",
        "function_in_this_layer / role_in_this_layer"
      ]
    },
    "source_chip": {
      "base_label": "Автоматическое ядро поведения",
      "pro_label": "Позиция активации · Солнце Дизайна",
      "short_role": "Показывает, какая тема может автоматически проявляться как центральный поведенческий паттерн.",
      "role_in_this_layer": "Эта позиция уточняет функцию данной темы в этом HR-слое: почему gate+line тема может быть важной для понимания наблюдаемого поведения, рабочего тона и того, как человек проявляется без обязательного self-report.",
      "link_target": "element://activation_role/design_sun"
    },
    "ai_digest": {
      "element_kind": "activation_role",
      "methodological_name": "activation_position",
      "element_key": "design_sun",
      "base_label": "Автоматическое ядро поведения",
      "pro_label": "Позиция активации · Солнце Дизайна",
      "layer_relevance": "Особенно релевантно для main_talents, work_style, development_potential, risks_and_distortions, management_and_environment и pro_foundation. Может быть релевантно для communication_and_influence или decision_and_stability, если gate/channel поддерживают эти слои.",
      "short_meaning": "Уточняет, что конкретная gate+line тема выполняет функцию автоматического центрального проявления: она может быть заметна в поведении, реакциях, рабочем тоне и наблюдаемом паттерне.",
      "healthy_expression_summary": "Человек естественно проявляет эту тему в поведении, а среда видит повторяемый рабочий вклад без необходимости постоянно требовать объяснений или самоанализа.",
      "distorted_expression_summary": "Тема может искажаться, если её превращают в ярлык, требуют полного осознанного объяснения или читают как постоянное качество без учёта среды, нагрузки и контекста.",
      "talent_hints": [
        "автоматическая центральная тема поведения",
        "повторяемый рабочий паттерн",
        "тема, которую могут замечать другие",
        "ценность, проявленная через действия",
        "различение self-report и наблюдаемого проявления"
      ],
      "risk_hints": [
        "ярлык по поведению",
        "требование объяснять автоматическую тему",
        "реакция под нагрузкой вместо устойчивого паттерна",
        "недооценка темы из-за слабого self-report",
        "ошибочное чтение Design как проблемы"
      ],
      "management_hints": [
        "наблюдать реальные рабочие ситуации",
        "обсуждать факты поведения мягко и конкретно",
        "не требовать мгновенного объяснения",
        "сверять наблюдения с результатами",
        "давать контекст для естественного проявления темы"
      ],
      "environment_hints": [
        "задачи, где тема проявляется естественно",
        "достаточно времени для наблюдения",
        "обратная связь по фактам",
        "отсутствие давления на мгновенный self-report",
        "среда, где автоматический вклад не превращают в ярлык"
      ],
      "key_limitations": [
        "не читать изолированно",
        "читать вместе с gate + line",
        "учитывать whole chart context",
        "Design не является слабостью",
        "Sun не равен всей карте"
      ],
      "must_read_with": [
        "gate",
        "line",
        "activation",
        "type",
        "strategy",
        "authority",
        "profile",
        "center",
        "channel, если gate входит в полный канал",
        "Earth activation when available",
        "observed behavior when available"
      ],
      "source_role": "supporting",
      "role_in_this_layer": "Уточняет функцию темы как автоматического центрального проявления внутри конкретного HR-слоя."
    }
  },
  "context_rules": {
    "primary_context": [
      "gate",
      "line",
      "side",
      "planet",
      "full activation key"
    ],
    "secondary_context": [
      "type",
      "strategy",
      "authority",
      "profile",
      "centers",
      "channels",
      "full channel or hanging gate context",
      "repeated gates / amplified themes",
      "observed behavior",
      "team feedback",
      "Earth activation context when available",
      "Incarnation Cross context when available"
    ],
    "depends_on": "design_sun раскрывается только через конкретную gate+line тему и общий контекст карты. Sun показывает центральность темы, Design показывает её автоматическую и поведенческую сторону, но итоговое значение зависит от всей механики карты, условий среды и реального поведения.",
    "related_element_kinds": [
      "gate",
      "line",
      "activation",
      "type",
      "strategy",
      "authority",
      "profile",
      "channel",
      "center",
      "activation_role"
    ],
    "context_note": "Не использовать design_sun как самостоятельный ярлык человека. Это функция темы в карте, а не итоговая HR-роль, профессия или решение о найме."
  },
  "not_self_layers": {
    "base": "Искажённое проявление возникает, когда автоматическую центральную тему читают без контекста, превращают в ярлык или требуют от человека полного осознанного объяснения того, что в первую очередь проявляется через поведение.",
    "pro": "Not-Self проявление возникает, когда Design Sun читается изолированно от gate, line, Strategy, Authority, channel context и whole chart context. Автоматическая тема может быть ошибочно принята за весь характер человека или за проблему, хотя она является частью механики проявления.",
    "warning_signals": [
      "наблюдаемое поведение превращают в жёсткий ярлык",
      "Design-позицию считают слабостью или проблемой",
      "от человека требуют полного объяснения автоматической темы",
      "реакцию под нагрузкой принимают за стабильную норму",
      "среда ожидает, что человек будет одинаково проявляться всегда",
      "AI читает design_sun без gate, line и whole chart context"
    ],
    "recovery_conditions": [
      "вернуть чтение к gate + line",
      "проверить, входит ли gate в полный канал",
      "учесть type / strategy / authority",
      "отделить автоматический паттерн от реакции на стресс",
      "проверить тему через повторяемое поведение, а не единичный эпизод",
      "определить source_role в конкретном HR-слое: primary / supporting / context_only"
    ]
  },
  "contrast_examples": [
    {
      "contrast_context": "design_sun vs personality_sun",
      "how_it_would_read": "design_sun чаще проявляется через действия, реакции, рабочий тон и то, что другие люди замечают в поведении.",
      "why_current_context_is_different": "personality_sun чаще проявляется через self-report, осознанное объяснение вклада и тему, с которой человек сам себя связывает."
    },
    {
      "contrast_context": "design_sun in full channel vs hanging gate",
      "how_it_would_read": "Если gate входит в полный канал, автоматическая центральная тема может быть более устойчивой и заметной как рабочий механизм.",
      "why_current_context_is_different": "Если gate висит отдельно, проявление темы может сильнее зависеть от среды, роли, партнёрских связок и конкретной ситуации."
    },
    {
      "contrast_context": "observed pattern vs single episode",
      "how_it_would_read": "Повторяемое поведение в разных рабочих ситуациях может быть важным подтверждением Design Sun.",
      "why_current_context_is_different": "Один эпизод под стрессом нельзя использовать как доказательство устойчивого автоматического паттерна."
    },
    {
      "contrast_context": "natural expression vs forced explanation",
      "how_it_would_read": "В здоровом контексте тема проявляется естественно через поведение и результат.",
      "why_current_context_is_different": "Если от человека требуют немедленно объяснить автоматическую тему, он может начать рационализировать или защищаться, и чтение станет менее точным."
    },
    {
      "contrast_context": "automatic behavior vs weakness",
      "how_it_would_read": "Design Sun может показывать ценный автоматический вклад, который хорошо виден в работе.",
      "why_current_context_is_different": "Ошибка — считать автоматичность слабостью, проблемой или отсутствием осознанности. Это слой проявления, который нужно читать через всю карту."
    }
  ]
}
